reedwolf/rules/__init__.py
reedwolf/rules/base.py
reedwolf/rules/components.py
reedwolf/rules/containers.py
reedwolf/rules/exceptions.py
reedwolf/rules/expressions.py
reedwolf/rules/models.py
reedwolf/rules/namespaces.py
reedwolf/rules/types.py
reedwolf/rules/utils.py
reedwolf/rules/validations.py
reedwolf/rules/variables.py
reedwolf.rules-0.0.1.dist-info/LICENSE
reedwolf.rules-0.0.1.dist-info/METADATA
reedwolf.rules-0.0.1.dist-info/WHEEL
reedwolf.rules-0.0.1.dist-info/top_level.txt
reedwolf.rules-0.0.1.dist-info/RECORD
