Metadata-Version: 2.1
Name: reedwolf.rules
Version: 0.0.1
Summary: A library that extends and enrich existing structured and unstructured data model with declarative constraints and automatic evaluation logic.
Home-page: https://github.com/trebor74hr/reedwolf.rules.git
Author: Robert Lujo
Author-email: trebor74hr@gmail.com
License: UNKNOWN
Platform: UNKNOWN
Classifier: Programming Language :: Python :: 3
Classifier: License :: OSI Approved :: MIT License
Classifier: Operating System :: OS Independent
Requires-Python: >=3.7
License-File: LICENSE
